setup.py
vnq/__init__.py
vnq/vnq.py
vnq.egg-info/PKG-INFO
vnq.egg-info/SOURCES.txt
vnq.egg-info/dependency_links.txt
vnq.egg-info/top_level.txt